synvya_sdk/__init__.py
synvya_sdk/models.py
synvya_sdk/models.pyi
synvya_sdk/nostr.py
synvya_sdk/nostr.pyi
synvya_sdk/py.typed
synvya_sdk/agno/__init__.py
synvya_sdk/agno/buyer.py
synvya_sdk/agno/buyer.pyi
synvya_sdk/agno/dadjokegamer.py
synvya_sdk/agno/dadjokegamer.pyi
synvya_sdk/agno/seller.py
synvya_sdk/agno/seller.pyi
synvya_sdk-0.3.7.dist-info/licenses/LICENSE
synvya_sdk-0.3.7.dist-info/METADATA
synvya_sdk-0.3.7.dist-info/WHEEL
synvya_sdk-0.3.7.dist-info/top_level.txt
synvya_sdk-0.3.7.dist-info/RECORD
